jbang/__init__.py
jbang/__main__.py
jbang/jbang.py
jbang-0.8.0.dist-info/METADATA
jbang-0.8.0.dist-info/WHEEL
jbang-0.8.0.dist-info/entry_points.txt
jbang-0.8.0.dist-info/top_level.txt
jbang-0.8.0.dist-info/RECORD
