Metadata-Version: 2.4
Name: jbang
Version: 0.8.0
Summary: Python for JBang - Java Script in your Python
Home-page: http://jbang.dev
Author: JBang Developers
Author-email: team@jbang.dev
License: MIT
Provides-Extra: test
Requires-Dist: pytest; extra == "test"
Dynamic: author
Dynamic: author-email
Dynamic: description
Dynamic: description-content-type
Dynamic: home-page
Dynamic: license
Dynamic: provides-extra
Dynamic: summary
